viyu_xmpp/__init__.py
viyu_xmpp/server.py
viyu_xmpp/stanza/__init__.py
viyu_xmpp/stanza/get_stanza.py
viyu_xmpp/stanza/post_stanza.py
viyu_xmpp-0.0.1.dist-info/METADATA
viyu_xmpp-0.0.1.dist-info/WHEEL
viyu_xmpp-0.0.1.dist-info/entry_points.txt
viyu_xmpp-0.0.1.dist-info/top_level.txt
viyu_xmpp-0.0.1.dist-info/RECORD
