Metadata-Version: 2.1
Name: viyu_xmpp
Version: 0.0.1
Summary: A package to manage XMPP server events and provide custom handlers for GET and POST stanzas.
Home-page: https://github.com/triyom-dev/viyu-xmpp-app
Author: TRIYOM SOFTWARES PVT LTD
Author-email: admin@triyom.in
Project-URL: Source, https://github.com/triyom-dev/viyu-xmpp-app
Project-URL: Bug Tracker, https://github.com/triyom-dev/viyu-xmpp-app/issues
Classifier: Development Status :: 3 - Alpha
Classifier: Programming Language :: Python :: 3
Classifier: Programming Language :: Python :: 3.6
Classifier: Programming Language :: Python :: 3.7
Classifier: Programming Language :: Python :: 3.8
Classifier: Programming Language :: Python :: 3.9
Classifier: License :: OSI Approved :: MIT License
Classifier: Operating System :: OS Independent
Classifier: Topic :: Communications
Classifier: Topic :: Internet
Requires-Python: >=3.6
Requires-Dist: slixmpp>=1.7.0
Requires-Dist: cryptography>=3.4.8
